itde/__init__.py
itde/containers.py
itde/endpoints.py
itde/exceptions.py
itde/extractor.py
itde/items.py
itde/types.py
itde/utils.py
itde/ytypes.py
itde-1.2.8.dist-info/LICENSE
itde-1.2.8.dist-info/METADATA
itde-1.2.8.dist-info/WHEEL
itde-1.2.8.dist-info/top_level.txt
itde-1.2.8.dist-info/RECORD
