Metadata-Version: 2.1
Name: itde
Version: 1.2.8
Summary: InnerTube Data Extractor
Home-page: https://github.com/g3nsy/itde
Author: Simone Gentili (g3nsy)
Author-email: 
License: MIT
Classifier: License :: OSI Approved :: MIT License
Classifier: Programming Language :: Python :: 3
Requires-Python: >=3.6.0
License-File: LICENSE
